{"cameraMode":{"drawMode":0,"name":"Shaded","section":"Shading Mode"},"sceneLighting":true,"audioPlay":false,"sceneViewState":{"m_AlwaysRefresh":false,"showFog":true,"showSkybox":true,"showFlares":true,"showImageEffects":true,"showParticleSystems":true,"showVisualEffectGraphs":true,"m_FxEnabled":true},"in2DMode":false,"pivot":{"x":-21.86180305480957,"y":5.429980278015137,"z":19.70846176147461},"rotation":{"x":0.11951792240142822,"y":-0.560194730758667,"z":0.08212239295244217,"w":0.8157523274421692},"size":0.8660253882408142,"orthographic":false}