{"cameraMode":{"drawMode":0,"name":"Shaded","section":"Shading Mode"},"sceneLighting":true,"audioPlay":false,"sceneViewState":{"m_AlwaysRefresh":false,"showFog":true,"showSkybox":true,"showFlares":true,"showImageEffects":true,"showParticleSystems":true,"showVisualEffectGraphs":true,"m_FxEnabled":true},"in2DMode":false,"pivot":{"x":-14.7952299118042,"y":0.14336924254894257,"z":-11.80185317993164},"rotation":{"x":0.07212897390127182,"y":0.5918477177619934,"z":-0.05364826321601868,"w":0.801120936870575},"size":0.36476293206214907,"orthographic":false}