{"cameraMode":{"drawMode":0,"name":"Shaded","section":"Shading Mode"},"sceneLighting":true,"audioPlay":false,"sceneViewState":{"m_AlwaysRefresh":false,"showFog":true,"showSkybox":true,"showFlares":true,"showImageEffects":true,"showParticleSystems":true,"showVisualEffectGraphs":true,"m_FxEnabled":true},"in2DMode":false,"pivot":{"x":-4.942343711853027,"y":-0.29496777057647707,"z":-9.563210487365723},"rotation":{"x":0.051075711846351626,"y":-0.9320904016494751,"z":0.14518477022647859,"w":0.3283025324344635},"size":5.169052600860596,"orthographic":false}