{"cameraMode":{"drawMode":0,"name":"Shaded","section":"Shading Mode"},"sceneLighting":true,"audioPlay":false,"sceneViewState":{"m_AlwaysRefresh":false,"showFog":true,"showSkybox":true,"showFlares":true,"showImageEffects":true,"showParticleSystems":true,"showVisualEffectGraphs":true,"m_FxEnabled":true},"in2DMode":false,"pivot":{"x":-8.213282585144043,"y":2.8825063705444338,"z":-4.723265647888184},"rotation":{"x":-0.13327540457248689,"y":0.06830742210149765,"z":-0.004531967453658581,"w":-0.9900904297828674},"size":1.1029019355773926,"orthographic":false}